Metadata-Version: 2.1
Name: safefilesystem
Version: 0.1.0
Summary: A Python module for safely working with the file system in a safe, auditable way.
Home-page: https://github.com/asweigart/safefs
Author: Al Sweigart
Author-email: al@inventwithpython.com
License: MIT
Platform: UNKNOWN
Classifier: License :: OSI Approved :: MIT License
Classifier: Programming Language :: Python
Classifier: Programming Language :: Python :: 3
Classifier: Programming Language :: Python :: 3.5
Classifier: Programming Language :: Python :: 3.6
Classifier: Programming Language :: Python :: 3.7
Classifier: Programming Language :: Python :: 3.8
Classifier: Programming Language :: Python :: 3.9
